dbt/adapters/spark_cde/.env
dbt/adapters/spark_cde/__init__.py
dbt/adapters/spark_cde/__version__.py
dbt/adapters/spark_cde/adaptertimer.py
dbt/adapters/spark_cde/cdeapisession.py
dbt/adapters/spark_cde/cloudera_tracking.py
dbt/adapters/spark_cde/column.py
dbt/adapters/spark_cde/connections.py
dbt/adapters/spark_cde/impl.py
dbt/adapters/spark_cde/python_submissions.py
dbt/adapters/spark_cde/relation.py
dbt/adapters/spark_cde/session.py
dbt/include/spark_cde/__init__.py
dbt/include/spark_cde/dbt_project.yml
dbt/include/spark_cde/profile_template.yml
dbt/include/spark_cde/macros/adapters.sql
dbt/include/spark_cde/macros/apply_grants.sql
dbt/include/spark_cde/macros/materializations/seed.sql
dbt/include/spark_cde/macros/materializations/snapshot.sql
dbt/include/spark_cde/macros/materializations/table.sql
dbt/include/spark_cde/macros/materializations/view.sql
dbt/include/spark_cde/macros/materializations/incremental/column_helpers.sql
dbt/include/spark_cde/macros/materializations/incremental/incremental.sql
dbt/include/spark_cde/macros/materializations/incremental/strategies.sql
dbt/include/spark_cde/macros/materializations/incremental/validate.sql
dbt/include/spark_cde/macros/utils/any_value.sql
dbt/include/spark_cde/macros/utils/array_append.sql
dbt/include/spark_cde/macros/utils/array_concat.sql
dbt/include/spark_cde/macros/utils/array_construct.sql
dbt/include/spark_cde/macros/utils/assert_not_null.sql
dbt/include/spark_cde/macros/utils/bool_or.sql
dbt/include/spark_cde/macros/utils/concat.sql
dbt/include/spark_cde/macros/utils/dateadd.sql
dbt/include/spark_cde/macros/utils/datediff.sql
dbt/include/spark_cde/macros/utils/intersect.sql
dbt/include/spark_cde/macros/utils/listagg.sql
dbt/include/spark_cde/macros/utils/split_part.sql
dbt/include/spark_cde/macros/utils/timestamps.sql
dbt_spark_cde-1.3.0.data/data/.env
dbt_spark_cde-1.3.0.dist-info/METADATA
dbt_spark_cde-1.3.0.dist-info/WHEEL
dbt_spark_cde-1.3.0.dist-info/top_level.txt
dbt_spark_cde-1.3.0.dist-info/RECORD
