Metadata-Version: 2.1
Name: dbt-spark-cde
Version: 1.3.0
Home-page: https://github.com/cloudera/dbt-spark-cde
Author: Cloudera
Author-email: innovation-feedback@cloudera.com
Classifier: Development Status :: 4 - Beta
Classifier: Operating System :: MacOS :: MacOS X
Classifier: Operating System :: Microsoft :: Windows
Classifier: Operating System :: POSIX :: Linux
Classifier: Programming Language :: Python :: 3.8
Classifier: Programming Language :: Python :: 3.9
Classifier: License :: OSI Approved :: Apache Software License
Requires-Python: >=3.7
Requires-Dist: dbt-core (~=1.3.0)
Requires-Dist: sqlparams (>=3.0.0)
Requires-Dist: requests (>=2.28.1)
Requires-Dist: requests-toolbelt (>=0.9.1)
Requires-Dist: python-decouple (>=3.6)
